apkg/__init__.py
apkg/__main__.py
apkg/adistro.py
apkg/cache.py
apkg/cli.py
apkg/compat.py
apkg/ex.py
apkg/log.py
apkg/parse.py
apkg/pkgstyle.py
apkg/pkgtemplate.py
apkg/pkgtest.py
apkg/project.py
apkg/terminal.py
apkg/commands/__init__.py
apkg/commands/build.py
apkg/commands/build_dep.py
apkg/commands/clean.py
apkg/commands/compat.py
apkg/commands/get_archive.py
apkg/commands/info.py
apkg/commands/install.py
apkg/commands/lint.py
apkg/commands/make_archive.py
apkg/commands/srcpkg.py
apkg/commands/status.py
apkg/commands/system_setup.py
apkg/commands/test.py
apkg/commands/test_dep.py
apkg/pkgstyles/__init__.py
apkg/pkgstyles/arch.py
apkg/pkgstyles/deb.py
apkg/pkgstyles/nix.py
apkg/pkgstyles/rpm.py
apkg/templatevars/__init__.py
apkg/templatevars/deb_series.py
apkg/templatevars/debseries.py
apkg/templatevars/distro_like.py
apkg/util/__init__.py
apkg/util/archive.py
apkg/util/common.py
apkg/util/git.py
apkg/util/run.py
apkg/util/serial.py
apkg/util/test.py
apkg/util/toml.py
apkg/util/upstreamversion.py
apkg-0.7.1.dist-info/licenses/COPYING
apkg-0.7.1.dist-info/METADATA
apkg-0.7.1.dist-info/WHEEL
apkg-0.7.1.dist-info/entry_points.txt
apkg-0.7.1.dist-info/top_level.txt
apkg-0.7.1.dist-info/RECORD
